PyWindowsGuiLibrary/PyWindowsGuiLibrary.py
PyWindowsGuiLibrary/__init__.py
robotframework_PyWindowsGuiLibrary-1.1.dist-info/LICENSE
robotframework_PyWindowsGuiLibrary-1.1.dist-info/METADATA
robotframework_PyWindowsGuiLibrary-1.1.dist-info/WHEEL
robotframework_PyWindowsGuiLibrary-1.1.dist-info/top_level.txt
robotframework_PyWindowsGuiLibrary-1.1.dist-info/RECORD
