Metadata-Version: 2.1
Name: robotframework-PyWindowsGuiLibrary
Version: 1.1
Summary: A Robot Framework Library for automating the WINDOWS BASED GUI applications
Home-page: https://github.com/HimaAne/robotframework-PyWindowsGuiLibrary/archive/refs/tags/1.4.tar.gz
Author: Himavanthudu Bodapati
Author-email: himavanthudu.b@gmail.com
License: UNKNOWN
Platform: UNKNOWN
Classifier: Programming Language :: Python :: 3.6
Classifier: Operating System :: Microsoft :: Windows
Requires-Dist: pywinauto (>=0.6.8)
Requires-Dist: robotframework (>=4.0.3)
Requires-Dist: pyautogui (>=0.9.53)
Requires-Dist: datetime (>=4.3)
